py_ed25519_bindings-1.0.2.dist-info/METADATA
py_ed25519_bindings-1.0.2.dist-info/WHEEL
ed25519_dalek/__init__.py
ed25519_dalek/ed25519_dalek.pyd
py_ed25519_bindings-1.0.2.dist-info/RECORD
