Metadata-Version: 2.1
Name: py-ed25519-bindings
Version: 1.0.2
Classifier: License :: OSI Approved :: Apache Software License
Classifier: Intended Audience :: Developers
Classifier: Programming Language :: Python :: 3
Classifier: Programming Language :: Python :: 3.6
Classifier: Programming Language :: Python :: 3.7
Classifier: Programming Language :: Python :: 3.8
Classifier: Programming Language :: Python :: 3.9
Classifier: Programming Language :: Python :: 3.10
Summary: Python bindings for the ed25519-dalek RUST crate
Home-Page: https://github.com/polkascan/py-ed25519-bindings
Author: Stichting Polkascan (Polkascan Foundation)
Maintainer: Stichting Polkascan (Polkascan Foundation)
Maintainer-email: legal@polkascan.org
License: Apache-2.0
Project-URL: Source Code, https://github.com/polkascan/py-ed25519-bindings
